rpca/__init__.py
rpca/rpca.py
rpca/util.py
rpca-0.1.5.dist-info/LICENSE
rpca-0.1.5.dist-info/METADATA
rpca-0.1.5.dist-info/WHEEL
rpca-0.1.5.dist-info/RECORD
