Metadata-Version: 2.1
Name: rpca
Version: 0.1.5
Summary: Robust PCA using Accelerated Alternating Projection
Home-page: https://github.com/loiccoyle/RPCA
License: MIT
Author: Loic Coyle
Author-email: loic.coyle@hotmail.fr
Requires-Python: >=3.9,<3.13
Classifier: License :: OSI Approved :: MIT License
Classifier: Operating System :: MacOS
Classifier: Operating System :: Microsoft :: Windows
Classifier: Operating System :: POSIX :: Linux
Classifier: Programming Language :: Python :: 3
Classifier: Programming Language :: Python :: 3.9
Classifier: Programming Language :: Python :: 3.10
Classifier: Programming Language :: Python :: 3.11
Classifier: Programming Language :: Python :: 3.12
Classifier: Programming Language :: Python :: 3 :: Only
Classifier: Topic :: Software Development :: Libraries :: Python Modules
Requires-Dist: numpy (>=1.26.0,<2.0.0)
Requires-Dist: scipy (>=1.11.3,<2.0.0)
Project-URL: Repository, https://github.com/loiccoyle/RPCA
